pycltools/__init__.py
pycltools/pycltools.py
pycltools-1.1.5.7.dist-info/LICENSE
pycltools-1.1.5.7.dist-info/METADATA
pycltools-1.1.5.7.dist-info/WHEEL
pycltools-1.1.5.7.dist-info/top_level.txt
pycltools-1.1.5.7.dist-info/RECORD
